{
  "aid": "pocketbase",
  "url": "https://github.com/pocketbase/pocketbase/releases.atom",
  "type": "atom",
  "title": "PocketBase Releases",
  "description": "PocketBase release notes and changelog via GitHub Releases Atom feed.",
  "repo": "pocketbase",
  "feeds": [
    {
      "source": "https://github.com/pocketbase/pocketbase/releases.atom",
      "feed_url": "https://github.com/pocketbase/pocketbase/releases.atom",
      "title": "",
      "saved": 0,
      "method": "feed"
    },
    {
      "source": "https://github.com/pocketbase",
      "feed_url": "https://github.com/pocketbase",
      "title": "",
      "saved": 0,
      "method": "none"
    }
  ],
  "post_count": 11,
  "fetched": "2026-07-11T11:50:51Z"
}